{
    "date": "2025-12-10",
    "url": "https://nadaesgratis.es/admin/el-mercado-no-innova-solo-lecciones-de-la-politica-cientifica-estadounidense",
    "title": "El mercado no innova solo: lecciones de la política científica estadounidense",
    "content": "Por Andrea Gazzani (Bank of Italy), Joseba Martinez (London Business School y CEPR), Filippo Natoli (Bank of Italy) y Paolo Surico (London Business School y CEPR) Nota de los autores: Esta columna no refleja necesariamente las opiniones del Banco de Italia ni del Sistema Europeo de Bancos Centrales. En el debate público solemos asociar la [leer más ...]",
    "document_type": "rss"
}